{"objects":{"20210423105015":{"geometries":[{"coordinates":[11.29091273,45.67372608],"id":"v_fenomeni_pub.fid-73699495_178c6b4fb61_-61d4","type":"Point","properties":{"data_bollettino":"2021-04-22Z","id_fenomeno":2,"id_bollettino":202104231,"lon":11.290912732297977,"id":null,"lat":45.6737260791591}},{"coordinates":[8.8158758,45.08007783],"id":"v_fenomeni_pub.fid-73699495_178c6b4fb61_-61d3","type":"Point","properties":{"data_bollettino":"2021-04-22Z","id_fenomeno":2,"id_bollettino":202104231,"lon":8.81587579801146,"id":null,"lat":45.08007783106414}},{"coordinates":[10.94883446,45.17945202],"id":"v_fenomeni_pub.fid-73699495_178c6b4fb61_-61d2","type":"Point","properties":{"data_bollettino":"2021-04-22Z","id_fenomeno":2,"id_bollettino":202104231,"lon":10.948834456826734,"id":null,"lat":45.17945202488955}},{"coordinates":[11.61286876,45.22198796],"id":"v_fenomeni_pub.fid-73699495_178c6b4fb61_-61d1","type":"Point","properties":{"data_bollettino":"2021-04-22Z","id_fenomeno":2,"id_bollettino":202104231,"lon":11.612868756270068,"id":null,"lat":45.22198796401983}}],"type":"GeometryCollection"}},"type":"Topology","arcs":[]}