{"type":"FeatureCollection","features":[{"type":"Feature","id":"v_fenomeni_pub.fid--2e92ed42_17918358c4d_-219","geometry":{"type":"Point","coordinates":[8.41343077,44.62359094]},"geometry_name":"geom","properties":{"id":null,"id_bollettino":202105021,"data_bollettino":"2021-05-01Z","id_fenomeno":7,"lat":44.62359094303304,"lon":8.413430768046169}},{"type":"Feature","id":"v_fenomeni_pub.fid--2e92ed42_17918358c4d_-218","geometry":{"type":"Point","coordinates":[9.60064361,44.62359094]},"geometry_name":"geom","properties":{"id":null,"id_bollettino":202105021,"data_bollettino":"2021-05-01Z","id_fenomeno":7,"lat":44.62359094303304,"lon":9.600643606443608}},{"type":"Feature","id":"v_fenomeni_pub.fid--2e92ed42_17918358c4d_-217","geometry":{"type":"Point","coordinates":[11.04944571,44.13460953]},"geometry_name":"geom","properties":{"id":null,"id_bollettino":202105021,"data_bollettino":"2021-05-01Z","id_fenomeno":6,"lat":44.13460952965808,"lon":11.049445714318011}},{"type":"Feature","id":"v_fenomeni_pub.fid--2e92ed42_17918358c4d_-216","geometry":{"type":"Point","coordinates":[11.75372452,45.34940498]},"geometry_name":"geom","properties":{"id":null,"id_bollettino":202105021,"data_bollettino":"2021-05-01Z","id_fenomeno":31,"lat":45.34940498185747,"lon":11.753724516757856}}],"totalFeatures":4,"numberMatched":4,"numberReturned":4,"timeStamp":"2021-05-02T13:55:01.376Z","crs":{"type":"name","properties":{"name":"urn:ogc:def:crs:EPSG::4326"}}}